chianti_pearl-1.0.5.dist-info/METADATA
chianti_pearl-1.0.5.dist-info/RECORD
chianti_pearl-1.0.5.dist-info/WHEEL
chianti_pearl-1.0.5.dist-info/top_level.txt
pearl/__init__.py
pearl/core.py
pearl/parser.py
